zpp/__init__.py
zpp/registration.py
zpp/version.py
zpp/zpp.mk
zpp/cmake/TestFortType.cmake
zpp/cmake/Zpp.cmake
zpp/cmake/ZppConfig.cmake
zpp/cmake/ZppConfigVersion.cmake
zpp/include/base.zpp.sh
zpp/include/config.Gnu.zpp.sh
zpp/include/config.Intel.zpp.sh
zpp/include/config.PGI.zpp.sh
zpp/include/config.XL.zpp.sh
zpp/include/fortran.zpp.sh
zpp/include/hdf5_fortran.zpp.sh
zpp-1.1.0.dist-info/AUTHORS
zpp-1.1.0.dist-info/METADATA
zpp-1.1.0.dist-info/WHEEL
zpp-1.1.0.dist-info/entry_points.txt
zpp-1.1.0.dist-info/top_level.txt
zpp-1.1.0.dist-info/RECORD
