Metadata-Version: 2.1
Name: zpp
Version: 1.1.0
Summary: a Bash Pre-Processor for Fortran.ZPP is useful in order to build clean Fortran90 interfaces.It allows to generate Fortran code for all types, kinds, and array rankssupported by the compiler.
Author-email: Julien Bigot <julien.bigot@cea.fr>
License: MIT
Keywords: bash,Fortran,pre-processor
Classifier: License :: OSI Approved :: MIT License
Classifier: Development Status :: 5 - Production/Stable
Classifier: Environment :: Console
Requires-Python: >=3.10
License-File: AUTHORS
